binary_sbom/__init__.py
binary_sbom/analyzer.py
binary_sbom/cli.py
binary_sbom/config.py
binary_sbom/discovery.py
binary_sbom/eta_estimator.py
binary_sbom/filters.py
binary_sbom/generator.py
binary_sbom/parallel_processor.py
binary_sbom/path_validator.py
binary_sbom/progress.py
binary_sbom/progress_state.py
binary_sbom/progress_tracker.py
binary_sbom/secrets.py
binary_sbom/streaming_parser.py
binary_sbom/validator.py
binary_sbom/vulnerability.py
binary_sbom/clients/__init__.py
binary_sbom/clients/base.py
binary_sbom/clients/github.py
binary_sbom/clients/nvd.py
binary_sbom/clients/osv.py
binary_sbom/plugins/__init__.py
binary_sbom/plugins/api.py
binary_sbom/plugins/discovery.py
binary_sbom/plugins/hex_parser.py
binary_sbom/plugins/img_parser.py
binary_sbom/plugins/integration.py
binary_sbom/plugins/loader.py
binary_sbom/plugins/registry.py
binary_sbom/sandbox/__init__.py
binary_sbom/sandbox/config.py
binary_sbom/sandbox/errors.py
binary_sbom/sandbox/limits.py
binary_sbom/sandbox/manager.py
binary_sbom/sandbox/metrics.py
binary_sbom/sandbox/security_logger.py
binary_sbom/sandbox/tempfile.py
binary_sbom/sandbox/worker.py
binary_sbom/vulnscan/__init__.py
binary_sbom/vulnscan/exceptions.py
binary_sbom/vulnscan/types.py
binary_sbom/vulnscan/aggregation/__init__.py
binary_sbom/vulnscan/aggregation/deduplicator.py
binary_sbom/vulnscan/aggregation/filter.py
binary_sbom/vulnscan/aggregation/summarizer.py
binary_sbom/vulnscan/annotations/__init__.py
binary_sbom/vulnscan/annotations/annotation.py
binary_sbom/vulnscan/annotations/sbom_integration.py
binary_sbom/vulnscan/clients/__init__.py
binary_sbom/vulnscan/clients/github.py
binary_sbom/vulnscan/clients/nvd.py
binary_sbom/vulnscan/clients/osv.py
binary_sbom/vulnscan/config/__init__.py
binary_sbom/vulnscan/config/settings.py
binary_sbom/vulnscan/scanners/__init__.py
binary_sbom/vulnscan/scanners/scanner.py
binary_sbom/vulnscan/utils/__init__.py
binary_sbom/vulnscan/utils/cache.py
binary_sbom/vulnscan/utils/cancellation.py
binary_sbom-1.1.0.dist-info/LICENSE
binary_sbom-1.1.0.dist-info/METADATA
binary_sbom-1.1.0.dist-info/WHEEL
binary_sbom-1.1.0.dist-info/entry_points.txt
binary_sbom-1.1.0.dist-info/top_level.txt
binary_sbom-1.1.0.dist-info/RECORD
