Metadata-Version: 2.1
Name: binary-sbom
Version: 1.1.0
Summary: CLI tool for analyzing binary files and generating SPDX SBOM documents with real-time animated progress visualization and supply chain security features
Author: Binary SBOM Team
License: MIT
Project-URL: Homepage, https://github.com/example/binary-sbom-generator
Project-URL: Repository, https://github.com/example/binary-sbom-generator
Project-URL: Issues, https://github.com/example/binary-sbom-generator/issues
Keywords: sbom,spdx,binary,analysis,security,compliance
Classifier: Development Status :: 5 - Production/Stable
Classifier: Intended Audience :: Developers
Classifier: Topic :: Security
Classifier: Topic :: Software Development :: Build Tools
Classifier: License :: OSI Approved :: MIT License
Classifier: Programming Language :: Python :: 3
Classifier: Programming Language :: Python :: 3.8
Classifier: Programming Language :: Python :: 3.9
Classifier: Programming Language :: Python :: 3.10
Classifier: Programming Language :: Python :: 3.11
Classifier: Programming Language :: Python :: 3.12
Requires-Python: >=3.8
License-File: LICENSE
Requires-Dist: click>=8.0.0
Requires-Dist: lief>=0.12.0
Requires-Dist: spdx-tools>=0.7.0
Requires-Dist: pyyaml>=6.0
Requires-Dist: cryptography>=41.0.0
Requires-Dist: requests>=2.31.0
Requires-Dist: rich>=13.0.0
Provides-Extra: dev
Requires-Dist: pytest>=7.0.0; extra == "dev"
Requires-Dist: pytest-cov>=4.0.0; extra == "dev"
Requires-Dist: mypy>=1.0.0; extra == "dev"
Requires-Dist: flake8>=6.0.0; extra == "dev"
Requires-Dist: black>=23.0.0; extra == "dev"
Requires-Dist: safety>=2.0.0; extra == "dev"
Requires-Dist: pip-audit>=2.0.0; extra == "dev"
Requires-Dist: bandit>=1.7.0; extra == "dev"
Requires-Dist: cyclonedx-bom>=4.0.0; extra == "dev"
